graphxr_database_proxy/__init__.py
graphxr_database_proxy/launcher.py
graphxr_database_proxy/main.py
graphxr_database_proxy/proxy.py
graphxr_database_proxy/proxyForDev.py
graphxr_database_proxy/api/__init__.py
graphxr_database_proxy/api/admin.py
graphxr_database_proxy/api/auth.py
graphxr_database_proxy/api/database.py
graphxr_database_proxy/api/google.py
graphxr_database_proxy/api/projects.py
graphxr_database_proxy/api/settings.py
graphxr_database_proxy/common/util.py
graphxr_database_proxy/drivers/__init__.py
graphxr_database_proxy/drivers/base.py
graphxr_database_proxy/drivers/factory.py
graphxr_database_proxy/drivers/spanner.py
graphxr_database_proxy/models/__init__.py
graphxr_database_proxy/models/google.py
graphxr_database_proxy/models/project.py
graphxr_database_proxy/services/__init__.py
graphxr_database_proxy/services/project_service.py
graphxr_database_proxy/services/settings_service.py
graphxr_database_proxy-1.1.0.dist-info/licenses/LICENSE
graphxr_database_proxy-1.1.0.dist-info/METADATA
graphxr_database_proxy-1.1.0.dist-info/WHEEL
graphxr_database_proxy-1.1.0.dist-info/entry_points.txt
graphxr_database_proxy-1.1.0.dist-info/top_level.txt
graphxr_database_proxy-1.1.0.dist-info/RECORD
