Metadata-Version: 2.4
Name: graphxr-database-proxy
Version: 1.1.0
Summary: GraphXR Database Proxy - Secure middleware for connecting GraphXR to databases
Author-email: Sean Li <sean@kineviz.com>, Kineviz <support@kineviz.com>
License-Expression: MIT
Project-URL: Homepage, https://github.com/Kineviz/graphxr-database-proxy
Project-URL: Documentation, https://docs.kineviz.com/graphxr-database-proxy
Project-URL: Repository, https://github.com/Kineviz/graphxr-database-proxy
Project-URL: Bug Tracker, https://github.com/Kineviz/graphxr-database-proxy/issues
Classifier: Development Status :: 4 - Beta
Classifier: Intended Audience :: Developers
Classifier: Programming Language :: Python :: 3
Classifier: Programming Language :: Python :: 3.9
Classifier: Programming Language :: Python :: 3.10
Classifier: Programming Language :: Python :: 3.11
Classifier: Programming Language :: Python :: 3.12
Classifier: Programming Language :: Python :: 3.13
Requires-Python: >=3.9
License-File: LICENSE
Requires-Dist: fastapi>=0.104.0
Requires-Dist: uvicorn[standard]>=0.24.0
Requires-Dist: pydantic>=2.0.0
Requires-Dist: python-multipart>=0.0.6
Requires-Dist: python-dotenv>=1.0.0
Requires-Dist: google-cloud-spanner>=3.40.0
Requires-Dist: google-cloud-resource-manager>=1.10.0
Requires-Dist: google-auth-oauthlib>=1.0.0
Requires-Dist: google-auth>=2.0.0
Requires-Dist: aiofiles>=23.0.0
Requires-Dist: pyyaml>=6.0
Provides-Extra: ui
Requires-Dist: aiofiles>=23.0.0; extra == "ui"
Provides-Extra: dev
Requires-Dist: pytest>=7.0.0; extra == "dev"
Requires-Dist: pytest-asyncio>=0.21.0; extra == "dev"
Requires-Dist: pytest-cov>=4.0.0; extra == "dev"
Requires-Dist: black>=23.0.0; extra == "dev"
Requires-Dist: isort>=5.12.0; extra == "dev"
Requires-Dist: flake8>=6.0.0; extra == "dev"
Requires-Dist: mypy>=1.5.0; extra == "dev"
Requires-Dist: pre-commit>=3.0.0; extra == "dev"
Provides-Extra: all
Requires-Dist: graphxr-database-proxy[dev,ui]; extra == "all"
Dynamic: license-file
